[
    {
        "id": 8073,
        "name": "Digah",
        "state_id": 540,
        "state_code": "ABS",
        "state_name": "Absheron",
        "country_id": 16,
        "country_code": "AZ",
        "country_name": "Azerbaijan",
        "latitude": "40.49257000",
        "longitude": "49.87477000",
        "timezone": null,
        "wikiDataId": "Q4120921"
    },
    {
        "id": 8085,
        "name": "Gyuzdek",
        "state_id": 540,
        "state_code": "ABS",
        "state_name": "Absheron",
        "country_id": 16,
        "country_code": "AZ",
        "country_name": "Azerbaijan",
        "latitude": "40.37444000",
        "longitude": "49.68194000",
        "timezone": null,
        "wikiDataId": "Q2352148"
    },
    {
        "id": 8099,
        "name": "Khirdalan",
        "state_id": 540,
        "state_code": "ABS",
        "state_name": "Absheron",
        "country_id": 16,
        "country_code": "AZ",
        "country_name": "Azerbaijan",
        "latitude": "40.44808000",
        "longitude": "49.75502000",
        "timezone": null,
        "wikiDataId": "Q642109"
    },
    {
        "id": 8148,
        "name": "Qobu",
        "state_id": 540,
        "state_code": "ABS",
        "state_name": "Absheron",
        "country_id": 16,
        "country_code": "AZ",
        "country_name": "Azerbaijan",
        "latitude": "40.40472000",
        "longitude": "49.71306000",
        "timezone": null,
        "wikiDataId": "Q4120862"
    },
    {
        "id": 8169,
        "name": "Saray",
        "state_id": 540,
        "state_code": "ABS",
        "state_name": "Absheron",
        "country_id": 16,
        "country_code": "AZ",
        "country_name": "Azerbaijan",
        "latitude": "40.53299000",
        "longitude": "49.71681000",
        "timezone": null,
        "wikiDataId": "Q4120861"
    },
    {
        "id": 8049,
        "name": "Ağdam",
        "state_id": 559,
        "state_code": "AGM",
        "state_name": "Agdam",
        "country_id": 16,
        "country_code": "AZ",
        "country_name": "Azerbaijan",
        "latitude": "39.99096000",
        "longitude": "46.92736000",
        "timezone": null,
        "wikiDataId": "Q540844"
    },
    {
        "id": 8050,
        "name": "Ağdaş",
        "state_id": 553,
        "state_code": "AGS",
        "state_name": "Agdash",
        "country_id": 16,
        "country_code": "AZ",
        "country_name": "Azerbaijan",
        "latitude": "40.64699000",
        "longitude": "47.47380000",
        "timezone": null,
        "wikiDataId": "Q1983932"
    },
    {
        "id": 8037,
        "name": "Agdzhabedy",
        "state_id": 577,
        "state_code": "AGC",
        "state_name": "Aghjabadi",
        "country_id": 16,
        "country_code": "AZ",
        "country_name": "Azerbaijan",
        "latitude": "40.05015000",
        "longitude": "47.45937000",
        "timezone": null,
        "wikiDataId": "Q1983875"
    },
    {
        "id": 8048,
        "name": "Avşar",
        "state_id": 577,
        "state_code": "AGC",
        "state_name": "Aghjabadi",
        "country_id": 16,
        "country_code": "AZ",
        "country_name": "Azerbaijan",
        "latitude": "39.97389000",
        "longitude": "47.42389000",
        "timezone": null,
        "wikiDataId": "Q21979202"
    },
    {
        "id": 8038,
        "name": "Aghstafa",
        "state_id": 543,
        "state_code": "AGA",
        "state_name": "Agstafa",
        "country_id": 16,
        "country_code": "AZ",
        "country_name": "Azerbaijan",
        "latitude": "41.11889000",
        "longitude": "45.45389000",
        "timezone": null,
        "wikiDataId": "Q1976493"
    },
    {
        "id": 8163,
        "name": "Saloğlu",
        "state_id": 543,
        "state_code": "AGA",
        "state_name": "Agstafa",
        "country_id": 16,
        "country_code": "AZ",
        "country_name": "Azerbaijan",
        "latitude": "41.27524000",
        "longitude": "45.35293000",
        "timezone": null,
        "wikiDataId": "Q4618136"
    },
    {
        "id": 8188,
        "name": "Vurğun",
        "state_id": 543,
        "state_code": "AGA",
        "state_name": "Agstafa",
        "country_id": 16,
        "country_code": "AZ",
        "country_name": "Azerbaijan",
        "latitude": "41.09524000",
        "longitude": "45.47111000",
        "timezone": null,
        "wikiDataId": "Q4120923"
    },
    {
        "id": 8039,
        "name": "Aghsu",
        "state_id": 547,
        "state_code": "AGU",
        "state_name": "Agsu",
        "country_id": 16,
        "country_code": "AZ",
        "country_name": "Azerbaijan",
        "latitude": "40.57028000",
        "longitude": "48.40087000",
        "timezone": null,
        "wikiDataId": "Q1976493"
    },
    {
        "id": 8047,
        "name": "Astara",
        "state_id": 528,
        "state_code": "AST",
        "state_name": "Astara",
        "country_id": 16,
        "country_code": "AZ",
        "country_name": "Azerbaijan",
        "latitude": "38.45598000",
        "longitude": "48.87498000",
        "timezone": null,
        "wikiDataId": "Q266896"
    },
    {
        "id": 8103,
        "name": "Kizhaba",
        "state_id": 528,
        "state_code": "AST",
        "state_name": "Astara",
        "country_id": 16,
        "country_code": "AZ",
        "country_name": "Azerbaijan",
        "latitude": "38.53461000",
        "longitude": "48.80546000",
        "timezone": null,
        "wikiDataId": "Q3674715"
    },
    {
        "id": 8042,
        "name": "Amirdzhan",
        "state_id": 552,
        "state_code": "BA",
        "state_name": "Baku",
        "country_id": 16,
        "country_code": "AZ",
        "country_name": "Azerbaijan",
        "latitude": "40.42639000",
        "longitude": "49.98361000",
        "timezone": null,
        "wikiDataId": "Q3131176"
    },
    {
        "id": 8051,
        "name": "Badamdar",
        "state_id": 552,
        "state_code": "BA",
        "state_name": "Baku",
        "country_id": 16,
        "country_code": "AZ",
        "country_name": "Azerbaijan",
        "latitude": "40.34024000",
        "longitude": "49.80450000",
        "timezone": null,
        "wikiDataId": "Q10860191"
    },
    {
        "id": 8053,
        "name": "Bakıxanov",
        "state_id": 552,
        "state_code": "BA",
        "state_name": "Baku",
        "country_id": 16,
        "country_code": "AZ",
        "country_name": "Azerbaijan",
        "latitude": "40.41894000",
        "longitude": "49.96693000",
        "timezone": null,
        "wikiDataId": "Q3299602"
    },
    {
        "id": 8052,
        "name": "Baku",
        "state_id": 552,
        "state_code": "BA",
        "state_name": "Baku",
        "country_id": 16,
        "country_code": "AZ",
        "country_name": "Azerbaijan",
        "latitude": "40.37767000",
        "longitude": "49.89201000",
        "timezone": null,
        "wikiDataId": "Q10860191"
    },
    {
        "id": 8054,
        "name": "Balakhani",
        "state_id": 552,
        "state_code": "BA",
        "state_name": "Baku",
        "country_id": 16,
        "country_code": "AZ",
        "country_name": "Azerbaijan",
        "latitude": "40.46344000",
        "longitude": "49.91893000",
        "timezone": null,
        "wikiDataId": "Q2081104"
    },
    {
        "id": 8060,
        "name": "Bilajari",
        "state_id": 552,
        "state_code": "BA",
        "state_name": "Baku",
        "country_id": 16,
        "country_code": "AZ",
        "country_name": "Azerbaijan",
        "latitude": "40.44440000",
        "longitude": "49.80566000",
        "timezone": null,
        "wikiDataId": "Q21980868"
    },
    {
        "id": 8061,
        "name": "Bilajer",
        "state_id": 552,
        "state_code": "BA",
        "state_name": "Baku",
        "country_id": 16,
        "country_code": "AZ",
        "country_name": "Azerbaijan",
        "latitude": "40.56441000",
        "longitude": "50.04002000",
        "timezone": null,
        "wikiDataId": "Q4026907"
    },
    {
        "id": 8062,
        "name": "Binagadi",
        "state_id": 552,
        "state_code": "BA",
        "state_name": "Baku",
        "country_id": 16,
        "country_code": "AZ",
        "country_name": "Azerbaijan",
        "latitude": "40.46602000",
        "longitude": "49.82783000",
        "timezone": null,
        "wikiDataId": "Q864153"
    },
    {
        "id": 8063,
        "name": "Biny Selo",
        "state_id": 552,
        "state_code": "BA",
        "state_name": "Baku",
        "country_id": 16,
        "country_code": "AZ",
        "country_name": "Azerbaijan",
        "latitude": "40.45076000",
        "longitude": "50.08686000",
        "timezone": null,
        "wikiDataId": "Q2339034"
    },
    {
        "id": 8066,
        "name": "Buzovna",
        "state_id": 552,
        "state_code": "BA",
        "state_name": "Baku",
        "country_id": 16,
        "country_code": "AZ",
        "country_name": "Azerbaijan",
        "latitude": "40.51903000",
        "longitude": "50.11438000",
        "timezone": null,
        "wikiDataId": "Q2671322"
    },
    {
        "id": 8093,
        "name": "Hövsan",
        "state_id": 552,
        "state_code": "BA",
        "state_name": "Baku",
        "country_id": 16,
        "country_code": "AZ",
        "country_name": "Azerbaijan",
        "latitude": "40.37444000",
        "longitude": "50.08528000",
        "timezone": null,
        "wikiDataId": "Q3294097"
    },
    {
        "id": 8100,
        "name": "Khodzhi-Gasan",
        "state_id": 552,
        "state_code": "BA",
        "state_name": "Baku",
        "country_id": 16,
        "country_code": "AZ",
        "country_name": "Azerbaijan",
        "latitude": "40.41293000",
        "longitude": "49.76904000",
        "timezone": null,
        "wikiDataId": "Q3951539"
    },
    {
        "id": 8104,
        "name": "Korgöz",
        "state_id": 552,
        "state_code": "BA",
        "state_name": "Baku",
        "country_id": 16,
        "country_code": "AZ",
        "country_name": "Azerbaijan",
        "latitude": "40.30446000",
        "longitude": "49.62360000",
        "timezone": null,
        "wikiDataId": "Q6432243"
    },
    {
        "id": 8111,
        "name": "Lökbatan",
        "state_id": 552,
        "state_code": "BA",
        "state_name": "Baku",
        "country_id": 16,
        "country_code": "AZ",
        "country_name": "Azerbaijan",
        "latitude": "40.32560000",
        "longitude": "49.73376000",
        "timezone": null,
        "wikiDataId": "Q2027140"
    },
    {
        "id": 8113,
        "name": "Mardakan",
        "state_id": 552,
        "state_code": "BA",
        "state_name": "Baku",
        "country_id": 16,
        "country_code": "AZ",
        "country_name": "Azerbaijan",
        "latitude": "40.49182000",
        "longitude": "50.14292000",
        "timezone": null,
        "wikiDataId": "Q1026043"
    },
    {
        "id": 8116,
        "name": "Maştağa",
        "state_id": 552,
        "state_code": "BA",
        "state_name": "Baku",
        "country_id": 16,
        "country_code": "AZ",
        "country_name": "Azerbaijan",
        "latitude": "40.52983000",
        "longitude": "50.00616000",
        "timezone": null,
        "wikiDataId": "Q4026905"
    },
    {
        "id": 8121,
        "name": "Nardaran",
        "state_id": 552,
        "state_code": "BA",
        "state_name": "Baku",
        "country_id": 16,
        "country_code": "AZ",
        "country_name": "Azerbaijan",
        "latitude": "40.55611000",
        "longitude": "50.00556000",
        "timezone": null,
        "wikiDataId": "Q1965248"
    },
    {
        "id": 8123,
        "name": "Nizami Rayonu",
        "state_id": 552,
        "state_code": "BA",
        "state_name": "Baku",
        "country_id": 16,
        "country_code": "AZ",
        "country_name": "Azerbaijan",
        "latitude": "40.40970000",
        "longitude": "49.91926000",
        "timezone": null,
        "wikiDataId": "Q3912215"
    },
    {
        "id": 8131,
        "name": "Pirallahı",
        "state_id": 552,
        "state_code": "BA",
        "state_name": "Baku",
        "country_id": 16,
        "country_code": "AZ",
        "country_name": "Azerbaijan",
        "latitude": "40.47013000",
        "longitude": "50.32476000",
        "timezone": null,
        "wikiDataId": "Q1017630"
    },
    {
        "id": 8134,
        "name": "Puta",
        "state_id": 552,
        "state_code": "BA",
        "state_name": "Baku",
        "country_id": 16,
        "country_code": "AZ",
        "country_name": "Azerbaijan",
        "latitude": "40.29667000",
        "longitude": "49.66028000",
        "timezone": null,
        "wikiDataId": "Q4026827"
    },
    {
        "id": 8136,
        "name": "Qala",
        "state_id": 552,
        "state_code": "BA",
        "state_name": "Baku",
        "country_id": 16,
        "country_code": "AZ",
        "country_name": "Azerbaijan",
        "latitude": "40.44256000",
        "longitude": "50.16759000",
        "timezone": null,
        "wikiDataId": "Q4026864"
    },
    {
        "id": 8142,
        "name": "Qaraçuxur",
        "state_id": 552,
        "state_code": "BA",
        "state_name": "Baku",
        "country_id": 16,
        "country_code": "AZ",
        "country_name": "Azerbaijan",
        "latitude": "40.39667000",
        "longitude": "49.97361000",
        "timezone": null,
        "wikiDataId": "Q685398"
    },
    {
        "id": 8149,
        "name": "Qobustan",
        "state_id": 552,
        "state_code": "BA",
        "state_name": "Baku",
        "country_id": 16,
        "country_code": "AZ",
        "country_name": "Azerbaijan",
        "latitude": "40.08238000",
        "longitude": "49.41205000",
        "timezone": null,
        "wikiDataId": "Q685724"
    },
    {
        "id": 8159,
        "name": "Ramana",
        "state_id": 552,
        "state_code": "BA",
        "state_name": "Baku",
        "country_id": 16,
        "country_code": "AZ",
        "country_name": "Azerbaijan",
        "latitude": "40.44222000",
        "longitude": "49.98056000",
        "timezone": null,
        "wikiDataId": "Q1013460"
    },
    {
        "id": 8162,
        "name": "Sabunçu",
        "state_id": 552,
        "state_code": "BA",
        "state_name": "Baku",
        "country_id": 16,
        "country_code": "AZ",
        "country_name": "Azerbaijan",
        "latitude": "40.44250000",
        "longitude": "49.94806000",
        "timezone": null,
        "wikiDataId": "Q260503"
    },
    {
        "id": 8168,
        "name": "Sanqaçal",
        "state_id": 552,
        "state_code": "BA",
        "state_name": "Baku",
        "country_id": 16,
        "country_code": "AZ",
        "country_name": "Azerbaijan",
        "latitude": "40.16991000",
        "longitude": "49.46394000",
        "timezone": null,
        "wikiDataId": "Q4026953"
    },
    {
        "id": 8184,
        "name": "Türkan",
        "state_id": 552,
        "state_code": "BA",
        "state_name": "Baku",
        "country_id": 16,
        "country_code": "AZ",
        "country_name": "Azerbaijan",
        "latitude": "40.36460000",
        "longitude": "50.22075000",
        "timezone": null,
        "wikiDataId": "Q4026904"
    },
    {
        "id": 8197,
        "name": "Yeni Suraxanı",
        "state_id": 552,
        "state_code": "BA",
        "state_name": "Baku",
        "country_id": 16,
        "country_code": "AZ",
        "country_name": "Azerbaijan",
        "latitude": "40.43026000",
        "longitude": "50.03598000",
        "timezone": null,
        "wikiDataId": "Q1026631"
    },
    {
        "id": 8201,
        "name": "Zabrat",
        "state_id": 552,
        "state_code": "BA",
        "state_name": "Baku",
        "country_id": 16,
        "country_code": "AZ",
        "country_name": "Azerbaijan",
        "latitude": "40.47746000",
        "longitude": "49.94174000",
        "timezone": null,
        "wikiDataId": "Q4026836"
    },
    {
        "id": 8205,
        "name": "Zyrya",
        "state_id": 552,
        "state_code": "BA",
        "state_name": "Baku",
        "country_id": 16,
        "country_code": "AZ",
        "country_name": "Azerbaijan",
        "latitude": "40.36613000",
        "longitude": "50.29198000",
        "timezone": null,
        "wikiDataId": "Q4192310"
    },
    {
        "id": 8058,
        "name": "Belokany",
        "state_id": 560,
        "state_code": "BAL",
        "state_name": "Balakan",
        "country_id": 16,
        "country_code": "AZ",
        "country_name": "Azerbaijan",
        "latitude": "41.72626000",
        "longitude": "46.40478000",
        "timezone": null,
        "wikiDataId": "Q1989793"
    },
    {
        "id": 8135,
        "name": "Qabaqçöl",
        "state_id": 560,
        "state_code": "BAL",
        "state_name": "Balakan",
        "country_id": 16,
        "country_code": "AZ",
        "country_name": "Azerbaijan",
        "latitude": "41.75259000",
        "longitude": "46.27052000",
        "timezone": null,
        "wikiDataId": "Q4617479"
    },
    {
        "id": 8055,
        "name": "Barda",
        "state_id": 569,
        "state_code": "BAR",
        "state_name": "Barda",
        "country_id": 16,
        "country_code": "AZ",
        "country_name": "Azerbaijan",
        "latitude": "40.37577000",
        "longitude": "47.12619000",
        "timezone": null,
        "wikiDataId": "Q842869"
    },
    {
        "id": 8167,
        "name": "Samuxlu",
        "state_id": 569,
        "state_code": "BAR",
        "state_name": "Barda",
        "country_id": 16,
        "country_code": "AZ",
        "country_name": "Azerbaijan",
        "latitude": "40.50833000",
        "longitude": "47.16917000",
        "timezone": null,
        "wikiDataId": "Q4617177"
    },
    {
        "id": 8059,
        "name": "Beylagan",
        "state_id": 554,
        "state_code": "BEY",
        "state_name": "Beylagan",
        "country_id": 16,
        "country_code": "AZ",
        "country_name": "Azerbaijan",
        "latitude": "39.77556000",
        "longitude": "47.61861000",
        "timezone": null,
        "wikiDataId": "Q642164"
    },
    {
        "id": 8064,
        "name": "Birinci Aşıqlı",
        "state_id": 554,
        "state_code": "BEY",
        "state_name": "Beylagan",
        "country_id": 16,
        "country_code": "AZ",
        "country_name": "Azerbaijan",
        "latitude": "39.81917000",
        "longitude": "47.67944000",
        "timezone": null,
        "wikiDataId": "Q4617886"
    },
    {
        "id": 8078,
        "name": "Dünyamalılar",
        "state_id": 554,
        "state_code": "BEY",
        "state_name": "Beylagan",
        "country_id": 16,
        "country_code": "AZ",
        "country_name": "Azerbaijan",
        "latitude": "39.77278000",
        "longitude": "47.75889000",
        "timezone": null,
        "wikiDataId": "Q4621474"
    },
    {
        "id": 8128,
        "name": "Orjonikidze",
        "state_id": 554,
        "state_code": "BEY",
        "state_name": "Beylagan",
        "country_id": 16,
        "country_code": "AZ",
        "country_name": "Azerbaijan",
        "latitude": "39.63571000",
        "longitude": "47.71199000",
        "timezone": null,
        "wikiDataId": "Q21977623"
    },
    {
        "id": 8200,
        "name": "Yuxarı Aran",
        "state_id": 554,
        "state_code": "BEY",
        "state_name": "Beylagan",
        "country_id": 16,
        "country_code": "AZ",
        "country_name": "Azerbaijan",
        "latitude": "39.73361000",
        "longitude": "47.65500000",
        "timezone": null,
        "wikiDataId": "Q4636272"
    },
    {
        "id": 8133,
        "name": "Pushkino",
        "state_id": 532,
        "state_code": "BIL",
        "state_name": "Bilasuvar",
        "country_id": 16,
        "country_code": "AZ",
        "country_name": "Azerbaijan",
        "latitude": "39.45833000",
        "longitude": "48.54500000",
        "timezone": null,
        "wikiDataId": "Q2043938"
    },
    {
        "id": 8187,
        "name": "Verkhniy Dashkesan",
        "state_id": 561,
        "state_code": "DAS",
        "state_name": "Dashkasan",
        "country_id": 16,
        "country_code": "AZ",
        "country_name": "Azerbaijan",
        "latitude": "40.49357000",
        "longitude": "46.07175000",
        "timezone": null,
        "wikiDataId": "Q2660769"
    },
    {
        "id": 8199,
        "name": "Yukhary-Dashkesan",
        "state_id": 561,
        "state_code": "DAS",
        "state_name": "Dashkasan",
        "country_id": 16,
        "country_code": "AZ",
        "country_name": "Azerbaijan",
        "latitude": "40.52393000",
        "longitude": "46.08186000",
        "timezone": null,
        "wikiDataId": "Q2332472"
    },
    {
        "id": 8080,
        "name": "Fizuli",
        "state_id": 527,
        "state_code": "FUZ",
        "state_name": "Fizuli",
        "country_id": 16,
        "country_code": "AZ",
        "country_name": "Azerbaijan",
        "latitude": "39.60094000",
        "longitude": "47.14529000",
        "timezone": null,
        "wikiDataId": "Q1996181"
    },
    {
        "id": 8092,
        "name": "Horadiz",
        "state_id": 527,
        "state_code": "FUZ",
        "state_name": "Fizuli",
        "country_id": 16,
        "country_code": "AZ",
        "country_name": "Azerbaijan",
        "latitude": "39.45015000",
        "longitude": "47.33496000",
        "timezone": null,
        "wikiDataId": "Q2658391"
    },
    {
        "id": 8081,
        "name": "Ganja",
        "state_id": 585,
        "state_code": "GA",
        "state_name": "Ganja",
        "country_id": 16,
        "country_code": "AZ",
        "country_name": "Azerbaijan",
        "latitude": "40.68278000",
        "longitude": "46.36056000",
        "timezone": null,
        "wikiDataId": "Q1996181"
    },
    {
        "id": 8044,
        "name": "Arıqdam",
        "state_id": 589,
        "state_code": "GAD",
        "state_name": "Gədəbəy",
        "country_id": 16,
        "country_code": "AZ",
        "country_name": "Azerbaijan",
        "latitude": "40.59313000",
        "longitude": "45.79900000",
        "timezone": null,
        "wikiDataId": "Q4591265"
    },
    {
        "id": 8045,
        "name": "Arıqıran",
        "state_id": 589,
        "state_code": "GAD",
        "state_name": "Gədəbəy",
        "country_id": 16,
        "country_code": "AZ",
        "country_name": "Azerbaijan",
        "latitude": "40.53971000",
        "longitude": "45.61414000",
        "timezone": null,
        "wikiDataId": "Q4591863"
    },
    {
        "id": 8067,
        "name": "Böyük Qaramurad",
        "state_id": 589,
        "state_code": "GAD",
        "state_name": "Gədəbəy",
        "country_id": 16,
        "country_code": "AZ",
        "country_name": "Azerbaijan",
        "latitude": "40.57626000",
        "longitude": "45.63727000",
        "timezone": null,
        "wikiDataId": "Q4595126"
    },
    {
        "id": 8105,
        "name": "Kyadabek",
        "state_id": 589,
        "state_code": "GAD",
        "state_name": "Gədəbəy",
        "country_id": 16,
        "country_code": "AZ",
        "country_name": "Azerbaijan",
        "latitude": "40.57055000",
        "longitude": "45.81229000",
        "timezone": null,
        "wikiDataId": "Q2352160"
    },
    {
        "id": 8124,
        "name": "Novosaratovka",
        "state_id": 589,
        "state_code": "GAD",
        "state_name": "Gədəbəy",
        "country_id": 16,
        "country_code": "AZ",
        "country_name": "Azerbaijan",
        "latitude": "40.59811000",
        "longitude": "45.60079000",
        "timezone": null,
        "wikiDataId": "Q4593078"
    },
    {
        "id": 8150,
        "name": "Qobustan",
        "state_id": 573,
        "state_code": "QOB",
        "state_name": "Gobustan",
        "country_id": 16,
        "country_code": "AZ",
        "country_name": "Azerbaijan",
        "latitude": "40.53360000",
        "longitude": "48.92819000",
        "timezone": null,
        "wikiDataId": "Q764030"
    },
    {
        "id": 8084,
        "name": "Goranboy",
        "state_id": 551,
        "state_code": "GOR",
        "state_name": "Goranboy",
        "country_id": 16,
        "country_code": "AZ",
        "country_name": "Azerbaijan",
        "latitude": "40.61028000",
        "longitude": "46.78972000",
        "timezone": null,
        "wikiDataId": "Q2352148"
    },
    {
        "id": 8158,
        "name": "Qızılhacılı",
        "state_id": 551,
        "state_code": "GOR",
        "state_name": "Goranboy",
        "country_id": 16,
        "country_code": "AZ",
        "country_name": "Azerbaijan",
        "latitude": "40.57362000",
        "longitude": "46.84900000",
        "timezone": null,
        "wikiDataId": "Q4657516"
    },
    {
        "id": 8082,
        "name": "Geoktschai",
        "state_id": 531,
        "state_code": "GOY",
        "state_name": "Goychay",
        "country_id": 16,
        "country_code": "AZ",
        "country_name": "Azerbaijan",
        "latitude": "40.65055000",
        "longitude": "47.74219000",
        "timezone": null,
        "wikiDataId": "Q1822209"
    },
    {
        "id": 8196,
        "name": "Yelenendorf",
        "state_id": 574,
        "state_code": "GYG",
        "state_name": "Goygol",
        "country_id": 16,
        "country_code": "AZ",
        "country_name": "Azerbaijan",
        "latitude": "40.58584000",
        "longitude": "46.31890000",
        "timezone": null,
        "wikiDataId": "Q1026631"
    },
    {
        "id": 8088,
        "name": "Hacıqabul",
        "state_id": 571,
        "state_code": "HAC",
        "state_name": "Hajigabul",
        "country_id": 16,
        "country_code": "AZ",
        "country_name": "Azerbaijan",
        "latitude": "40.03874000",
        "longitude": "48.94286000",
        "timezone": null,
        "wikiDataId": "Q4846302"
    },
    {
        "id": 8119,
        "name": "Mughan",
        "state_id": 571,
        "state_code": "HAC",
        "state_name": "Hajigabul",
        "country_id": 16,
        "country_code": "AZ",
        "country_name": "Azerbaijan",
        "latitude": "40.09902000",
        "longitude": "48.81886000",
        "timezone": null,
        "wikiDataId": "Q230932"
    },
    {
        "id": 8094,
        "name": "Imishli",
        "state_id": 544,
        "state_code": "IMI",
        "state_name": "Imishli",
        "country_id": 16,
        "country_code": "AZ",
        "country_name": "Azerbaijan",
        "latitude": "39.87095000",
        "longitude": "48.05995000",
        "timezone": null,
        "wikiDataId": "Q1996815"
    },
    {
        "id": 8056,
        "name": "Basqal",
        "state_id": 564,
        "state_code": "ISM",
        "state_name": "Ismailli",
        "country_id": 16,
        "country_code": "AZ",
        "country_name": "Azerbaijan",
        "latitude": "40.75520000",
        "longitude": "48.39104000",
        "timezone": null,
        "wikiDataId": "Q4079031"
    },
    {
        "id": 8210,
        "name": "İsmayıllı",
        "state_id": 564,
        "state_code": "ISM",
        "state_name": "Ismailli",
        "country_id": 16,
        "country_code": "AZ",
        "country_name": "Azerbaijan",
        "latitude": "40.78485000",
        "longitude": "48.15141000",
        "timezone": null,
        "wikiDataId": "Q12712919"
    },
    {
        "id": 8096,
        "name": "Jebrail",
        "state_id": 570,
        "state_code": "CAB",
        "state_name": "Jabrayil",
        "country_id": 16,
        "country_code": "AZ",
        "country_name": "Azerbaijan",
        "latitude": "39.39917000",
        "longitude": "47.02835000",
        "timezone": null,
        "wikiDataId": "Q1020627"
    },
    {
        "id": 8095,
        "name": "Jalilabad",
        "state_id": 578,
        "state_code": "CAL",
        "state_name": "Jalilabad",
        "country_id": 16,
        "country_code": "AZ",
        "country_name": "Azerbaijan",
        "latitude": "39.20963000",
        "longitude": "48.49186000",
        "timezone": null,
        "wikiDataId": "Q1020627"
    },
    {
        "id": 8132,
        "name": "Prishibinskoye",
        "state_id": 578,
        "state_code": "CAL",
        "state_name": "Jalilabad",
        "country_id": 16,
        "country_code": "AZ",
        "country_name": "Azerbaijan",
        "latitude": "39.11998000",
        "longitude": "48.59383000",
        "timezone": null,
        "wikiDataId": "Q2656617"
    },
    {
        "id": 8098,
        "name": "Kerbakhiar",
        "state_id": 525,
        "state_code": "KAL",
        "state_name": "Kalbajar",
        "country_id": 16,
        "country_code": "AZ",
        "country_name": "Azerbaijan",
        "latitude": "40.10984000",
        "longitude": "46.04446000",
        "timezone": null,
        "wikiDataId": "Q1643630"
    },
    {
        "id": 8186,
        "name": "Vank",
        "state_id": 525,
        "state_code": "KAL",
        "state_name": "Kalbajar",
        "country_id": 16,
        "country_code": "AZ",
        "country_name": "Azerbaijan",
        "latitude": "40.05275000",
        "longitude": "46.54419000",
        "timezone": null,
        "wikiDataId": "Q2660769"
    },
    {
        "id": 8189,
        "name": "Xaçmaz",
        "state_id": 590,
        "state_code": "XAC",
        "state_name": "Khachmaz",
        "country_id": 16,
        "country_code": "AZ",
        "country_name": "Azerbaijan",
        "latitude": "41.46426000",
        "longitude": "48.80565000",
        "timezone": null,
        "wikiDataId": "Q1018160"
    },
    {
        "id": 8191,
        "name": "Xudat",
        "state_id": 590,
        "state_code": "XAC",
        "state_name": "Khachmaz",
        "country_id": 16,
        "country_code": "AZ",
        "country_name": "Azerbaijan",
        "latitude": "41.63052000",
        "longitude": "48.68161000",
        "timezone": null,
        "wikiDataId": "Q2996307"
    },
    {
        "id": 8041,
        "name": "Altıağac",
        "state_id": 537,
        "state_code": "XIZ",
        "state_name": "Khizi",
        "country_id": 16,
        "country_code": "AZ",
        "country_name": "Azerbaijan",
        "latitude": "40.85785000",
        "longitude": "48.93540000",
        "timezone": null,
        "wikiDataId": "Q4737076"
    },
    {
        "id": 8101,
        "name": "Khyzy",
        "state_id": 537,
        "state_code": "XIZ",
        "state_name": "Khizi",
        "country_id": 16,
        "country_code": "AZ",
        "country_name": "Azerbaijan",
        "latitude": "40.90847000",
        "longitude": "49.07481000",
        "timezone": null,
        "wikiDataId": "Q2468528"
    },
    {
        "id": 8102,
        "name": "Kilyazi",
        "state_id": 537,
        "state_code": "XIZ",
        "state_name": "Khizi",
        "country_id": 16,
        "country_code": "AZ",
        "country_name": "Azerbaijan",
        "latitude": "40.87392000",
        "longitude": "49.34376000",
        "timezone": null,
        "wikiDataId": "Q2468528"
    },
    {
        "id": 8213,
        "name": "Şuraabad",
        "state_id": 537,
        "state_code": "XIZ",
        "state_name": "Khizi",
        "country_id": 16,
        "country_code": "AZ",
        "country_name": "Azerbaijan",
        "latitude": "40.81990000",
        "longitude": "49.46774000",
        "timezone": null,
        "wikiDataId": "Q2159352"
    },
    {
        "id": 8046,
        "name": "Askyaran",
        "state_id": 524,
        "state_code": "XCI",
        "state_name": "Khojali",
        "country_id": 16,
        "country_code": "AZ",
        "country_name": "Azerbaijan",
        "latitude": "39.93910000",
        "longitude": "46.83161000",
        "timezone": null,
        "wikiDataId": "Q1433468"
    },
    {
        "id": 8190,
        "name": "Xocalı",
        "state_id": 524,
        "state_code": "XCI",
        "state_name": "Khojali",
        "country_id": 16,
        "country_code": "AZ",
        "country_name": "Azerbaijan",
        "latitude": "39.91297000",
        "longitude": "46.79028000",
        "timezone": null,
        "wikiDataId": "Q1018160"
    },
    {
        "id": 8106,
        "name": "Kyurdarmir",
        "state_id": 549,
        "state_code": "KUR",
        "state_name": "Kurdamir",
        "country_id": 16,
        "country_code": "AZ",
        "country_name": "Azerbaijan",
        "latitude": "40.34257000",
        "longitude": "48.15649000",
        "timezone": null,
        "wikiDataId": "Q1851063"
    },
    {
        "id": 8109,
        "name": "Laçın",
        "state_id": 541,
        "state_code": "LAC",
        "state_name": "Lachin",
        "country_id": 16,
        "country_code": "AZ",
        "country_name": "Azerbaijan",
        "latitude": "39.59881000",
        "longitude": "46.55045000",
        "timezone": null,
        "wikiDataId": "Q1000883"
    },
    {
        "id": 8090,
        "name": "Haftoni",
        "state_id": 558,
        "state_code": "LA",
        "state_name": "Lankaran",
        "country_id": 16,
        "country_code": "AZ",
        "country_name": "Azerbaijan",
        "latitude": "38.76325000",
        "longitude": "48.76223000",
        "timezone": null,
        "wikiDataId": "Q4134282"
    },
    {
        "id": 8108,
        "name": "Lankaran",
        "state_id": 558,
        "state_code": "LA",
        "state_name": "Lankaran",
        "country_id": 16,
        "country_code": "AZ",
        "country_name": "Azerbaijan",
        "latitude": "38.75428000",
        "longitude": "48.85062000",
        "timezone": null,
        "wikiDataId": "Q228811"
    },
    {
        "id": 8110,
        "name": "Lerik",
        "state_id": 546,
        "state_code": "LER",
        "state_name": "Lerik",
        "country_id": 16,
        "country_code": "AZ",
        "country_name": "Azerbaijan",
        "latitude": "38.77388000",
        "longitude": "48.41497000",
        "timezone": null,
        "wikiDataId": "Q1000883"
    },
    {
        "id": 8089,
        "name": "Hadrut",
        "state_id": 568,
        "state_code": "XVD",
        "state_name": "Martuni",
        "country_id": 16,
        "country_code": "AZ",
        "country_name": "Azerbaijan",
        "latitude": "39.52003000",
        "longitude": "47.03190000",
        "timezone": null,
        "wikiDataId": "Q157919"
    },
    {
        "id": 8125,
        "name": "Novyy Karanlug",
        "state_id": 568,
        "state_code": "XVD",
        "state_name": "Martuni",
        "country_id": 16,
        "country_code": "AZ",
        "country_name": "Azerbaijan",
        "latitude": "39.79496000",
        "longitude": "47.11170000",
        "timezone": null,
        "wikiDataId": "Q4593078"
    },
    {
        "id": 8155,
        "name": "Qırmızı Bazar",
        "state_id": 568,
        "state_code": "XVD",
        "state_name": "Martuni",
        "country_id": 16,
        "country_code": "AZ",
        "country_name": "Azerbaijan",
        "latitude": "39.67669000",
        "longitude": "46.95123000",
        "timezone": null,
        "wikiDataId": "Q2657762"
    },
    {
        "id": 8065,
        "name": "Boradigah",
        "state_id": 555,
        "state_code": "MAS",
        "state_name": "Masally",
        "country_id": 16,
        "country_code": "AZ",
        "country_name": "Azerbaijan",
        "latitude": "38.93013000",
        "longitude": "48.70920000",
        "timezone": null,
        "wikiDataId": "Q4093443"
    },
    {
        "id": 8115,
        "name": "Masally",
        "state_id": 555,
        "state_code": "MAS",
        "state_name": "Masally",
        "country_id": 16,
        "country_code": "AZ",
        "country_name": "Azerbaijan",
        "latitude": "39.03532000",
        "longitude": "48.66540000",
        "timezone": null,
        "wikiDataId": "Q794712"
    },
    {
        "id": 8118,
        "name": "Mingelchaur",
        "state_id": 580,
        "state_code": "MI",
        "state_name": "Mingachevir",
        "country_id": 16,
        "country_code": "AZ",
        "country_name": "Azerbaijan",
        "latitude": "40.76395000",
        "longitude": "47.05953000",
        "timezone": null,
        "wikiDataId": "Q230932"
    },
    {
        "id": 8068,
        "name": "Cahri",
        "state_id": 562,
        "state_code": "NX",
        "state_name": "Nakhchivan",
        "country_id": 16,
        "country_code": "AZ",
        "country_name": "Azerbaijan",
        "latitude": "39.34837000",
        "longitude": "45.41557000",
        "timezone": null,
        "wikiDataId": "Q4620218"
    },
    {
        "id": 8206,
        "name": "Çalxanqala",
        "state_id": 562,
        "state_code": "NX",
        "state_name": "Nakhchivan",
        "country_id": 16,
        "country_code": "AZ",
        "country_name": "Azerbaijan",
        "latitude": "39.44167000",
        "longitude": "45.28333000",
        "timezone": null,
        "wikiDataId": "Q4739286"
    },
    {
        "id": 8071,
        "name": "Culfa",
        "state_id": 562,
        "state_code": "NX",
        "state_name": "Nakhchivan",
        "country_id": 16,
        "country_code": "AZ",
        "country_name": "Azerbaijan",
        "latitude": "38.95397000",
        "longitude": "45.62961000",
        "timezone": null,
        "wikiDataId": "Q1013454"
    },
    {
        "id": 8072,
        "name": "Deste",
        "state_id": 562,
        "state_code": "NX",
        "state_name": "Nakhchivan",
        "country_id": 16,
        "country_code": "AZ",
        "country_name": "Azerbaijan",
        "latitude": "38.88375000",
        "longitude": "45.90963000",
        "timezone": null,
        "wikiDataId": "Q4808890"
    },
    {
        "id": 8091,
        "name": "Heydarabad",
        "state_id": 562,
        "state_code": "NX",
        "state_name": "Nakhchivan",
        "country_id": 16,
        "country_code": "AZ",
        "country_name": "Azerbaijan",
        "latitude": "39.72286000",
        "longitude": "44.84846000",
        "timezone": null,
        "wikiDataId": "Q1888054"
    },
    {
        "id": 8097,
        "name": "Julfa Rayon",
        "state_id": 562,
        "state_code": "NX",
        "state_name": "Nakhchivan",
        "country_id": 16,
        "country_code": "AZ",
        "country_name": "Azerbaijan",
        "latitude": "39.16667000",
        "longitude": "45.66667000",
        "timezone": null,
        "wikiDataId": "Q644035"
    },
    {
        "id": 8120,
        "name": "Nakhchivan",
        "state_id": 562,
        "state_code": "NX",
        "state_name": "Nakhchivan",
        "country_id": 16,
        "country_code": "AZ",
        "country_name": "Azerbaijan",
        "latitude": "39.20889000",
        "longitude": "45.41222000",
        "timezone": null,
        "wikiDataId": "Q230104"
    },
    {
        "id": 8129,
        "name": "Oğlanqala",
        "state_id": 562,
        "state_code": "NX",
        "state_name": "Nakhchivan",
        "country_id": 16,
        "country_code": "AZ",
        "country_name": "Azerbaijan",
        "latitude": "39.58694000",
        "longitude": "45.04611000",
        "timezone": null,
        "wikiDataId": "Q7116768"
    },
    {
        "id": 8126,
        "name": "Ordubad",
        "state_id": 562,
        "state_code": "NX",
        "state_name": "Nakhchivan",
        "country_id": 16,
        "country_code": "AZ",
        "country_name": "Azerbaijan",
        "latitude": "38.90961000",
        "longitude": "46.02274000",
        "timezone": null,
        "wikiDataId": "Q1000839"
    },
    {
        "id": 8127,
        "name": "Ordubad Rayon",
        "state_id": 562,
        "state_code": "NX",
        "state_name": "Nakhchivan",
        "country_id": 16,
        "country_code": "AZ",
        "country_name": "Azerbaijan",
        "latitude": "39.08333000",
        "longitude": "45.91667000",
        "timezone": null,
        "wikiDataId": "Q512623"
    },
    {
        "id": 8157,
        "name": "Qıvraq",
        "state_id": 562,
        "state_code": "NX",
        "state_name": "Nakhchivan",
        "country_id": 16,
        "country_code": "AZ",
        "country_name": "Azerbaijan",
        "latitude": "39.39939000",
        "longitude": "45.11513000",
        "timezone": null,
        "wikiDataId": "Q1849093"
    },
    {
        "id": 8211,
        "name": "Şahbuz",
        "state_id": 562,
        "state_code": "NX",
        "state_name": "Nakhchivan",
        "country_id": 16,
        "country_code": "AZ",
        "country_name": "Azerbaijan",
        "latitude": "39.40722000",
        "longitude": "45.57389000",
        "timezone": null,
        "wikiDataId": "Q2159352"
    },
    {
        "id": 8170,
        "name": "Sedarak",
        "state_id": 562,
        "state_code": "NX",
        "state_name": "Nakhchivan",
        "country_id": 16,
        "country_code": "AZ",
        "country_name": "Azerbaijan",
        "latitude": "39.71427000",
        "longitude": "44.88455000",
        "timezone": null,
        "wikiDataId": "Q4404519"
    },
    {
        "id": 8172,
        "name": "Shahbuz Rayon",
        "state_id": 562,
        "state_code": "NX",
        "state_name": "Nakhchivan",
        "country_id": 16,
        "country_code": "AZ",
        "country_name": "Azerbaijan",
        "latitude": "39.41667000",
        "longitude": "45.58333000",
        "timezone": null,
        "wikiDataId": "Q4077334"
    },
    {
        "id": 8175,
        "name": "Sharur City",
        "state_id": 562,
        "state_code": "NX",
        "state_name": "Nakhchivan",
        "country_id": 16,
        "country_code": "AZ",
        "country_name": "Azerbaijan",
        "latitude": "39.55298000",
        "longitude": "44.97993000",
        "timezone": null,
        "wikiDataId": "Q390783"
    },
    {
        "id": 8179,
        "name": "Sumbatan-diza",
        "state_id": 562,
        "state_code": "NX",
        "state_name": "Nakhchivan",
        "country_id": 16,
        "country_code": "AZ",
        "country_name": "Azerbaijan",
        "latitude": "38.94804000",
        "longitude": "45.82572000",
        "timezone": null,
        "wikiDataId": "Q4120917"
    },
    {
        "id": 8181,
        "name": "Tazakend",
        "state_id": 562,
        "state_code": "NX",
        "state_name": "Nakhchivan",
        "country_id": 16,
        "country_code": "AZ",
        "country_name": "Azerbaijan",
        "latitude": "39.15459000",
        "longitude": "45.44282000",
        "timezone": null,
        "wikiDataId": "Q2043944"
    },
    {
        "id": 8195,
        "name": "Yaycı",
        "state_id": 562,
        "state_code": "NX",
        "state_name": "Nakhchivan",
        "country_id": 16,
        "country_code": "AZ",
        "country_name": "Azerbaijan",
        "latitude": "38.94052000",
        "longitude": "45.73244000",
        "timezone": null,
        "wikiDataId": "Q4725222"
    },
    {
        "id": 8122,
        "name": "Neftçala",
        "state_id": 530,
        "state_code": "NEF",
        "state_name": "Neftchala",
        "country_id": 16,
        "country_code": "AZ",
        "country_name": "Azerbaijan",
        "latitude": "39.37680000",
        "longitude": "49.24700000",
        "timezone": null,
        "wikiDataId": "Q2087800"
    },
    {
        "id": 8171,
        "name": "Severo-Vostotchnyi Bank",
        "state_id": 530,
        "state_code": "NEF",
        "state_name": "Neftchala",
        "country_id": 16,
        "country_code": "AZ",
        "country_name": "Azerbaijan",
        "latitude": "39.41117000",
        "longitude": "49.24792000",
        "timezone": null,
        "wikiDataId": "Q4077334"
    },
    {
        "id": 8178,
        "name": "Sovetabad",
        "state_id": 530,
        "state_code": "NEF",
        "state_name": "Neftchala",
        "country_id": 16,
        "country_code": "AZ",
        "country_name": "Azerbaijan",
        "latitude": "39.33667000",
        "longitude": "49.21414000",
        "timezone": null,
        "wikiDataId": "Q4120917"
    },
    {
        "id": 8192,
        "name": "Xıllı",
        "state_id": 530,
        "state_code": "NEF",
        "state_name": "Neftchala",
        "country_id": 16,
        "country_code": "AZ",
        "country_name": "Azerbaijan",
        "latitude": "39.43012000",
        "longitude": "49.10166000",
        "timezone": null,
        "wikiDataId": "Q4120919"
    },
    {
        "id": 8130,
        "name": "Oğuz",
        "state_id": 556,
        "state_code": "OGU",
        "state_name": "Oghuz",
        "country_id": 16,
        "country_code": "AZ",
        "country_name": "Azerbaijan",
        "latitude": "41.07128000",
        "longitude": "47.46528000",
        "timezone": null,
        "wikiDataId": "Q1017630"
    },
    {
        "id": 8154,
        "name": "Qutqashen",
        "state_id": 542,
        "state_code": "QAB",
        "state_name": "Qabala",
        "country_id": 16,
        "country_code": "AZ",
        "country_name": "Azerbaijan",
        "latitude": "40.98247000",
        "longitude": "47.84909000",
        "timezone": null,
        "wikiDataId": "Q244236"
    },
    {
        "id": 8208,
        "name": "Çinarlı",
        "state_id": 526,
        "state_code": "QAX",
        "state_name": "Qakh",
        "country_id": 16,
        "country_code": "AZ",
        "country_name": "Azerbaijan",
        "latitude": "41.46965000",
        "longitude": "46.91582000",
        "timezone": null,
        "wikiDataId": "Q4830457"
    },
    {
        "id": 8144,
        "name": "Qax",
        "state_id": 526,
        "state_code": "QAX",
        "state_name": "Qakh",
        "country_id": 16,
        "country_code": "AZ",
        "country_name": "Azerbaijan",
        "latitude": "41.41826000",
        "longitude": "46.92043000",
        "timezone": null,
        "wikiDataId": "Q1017662"
    },
    {
        "id": 8145,
        "name": "Qax İngiloy",
        "state_id": 526,
        "state_code": "QAX",
        "state_name": "Qakh",
        "country_id": 16,
        "country_code": "AZ",
        "country_name": "Azerbaijan",
        "latitude": "41.42412000",
        "longitude": "46.93859000",
        "timezone": null,
        "wikiDataId": "Q4845996"
    },
    {
        "id": 8146,
        "name": "Qaxbaş",
        "state_id": 526,
        "state_code": "QAX",
        "state_name": "Qakh",
        "country_id": 16,
        "country_code": "AZ",
        "country_name": "Azerbaijan",
        "latitude": "41.43254000",
        "longitude": "46.96460000",
        "timezone": null,
        "wikiDataId": "Q3651697"
    },
    {
        "id": 8147,
        "name": "Qazax",
        "state_id": 521,
        "state_code": "QAZ",
        "state_name": "Qazakh",
        "country_id": 16,
        "country_code": "AZ",
        "country_name": "Azerbaijan",
        "latitude": "41.09246000",
        "longitude": "45.36561000",
        "timezone": null,
        "wikiDataId": "Q586758"
    },
    {
        "id": 8087,
        "name": "Hacıhüseynli",
        "state_id": 563,
        "state_code": "QBA",
        "state_name": "Quba",
        "country_id": 16,
        "country_code": "AZ",
        "country_name": "Azerbaijan",
        "latitude": "41.45639000",
        "longitude": "48.64889000",
        "timezone": null,
        "wikiDataId": "Q4846302"
    },
    {
        "id": 8151,
        "name": "Quba",
        "state_id": 563,
        "state_code": "QBA",
        "state_name": "Quba",
        "country_id": 16,
        "country_code": "AZ",
        "country_name": "Azerbaijan",
        "latitude": "41.36108000",
        "longitude": "48.51341000",
        "timezone": null,
        "wikiDataId": "Q647982"
    },
    {
        "id": 8152,
        "name": "Qubadlı",
        "state_id": 548,
        "state_code": "QBI",
        "state_name": "Qubadli",
        "country_id": 16,
        "country_code": "AZ",
        "country_name": "Azerbaijan",
        "latitude": "39.34441000",
        "longitude": "46.58183000",
        "timezone": null,
        "wikiDataId": "Q1017710"
    },
    {
        "id": 8153,
        "name": "Qusar",
        "state_id": 588,
        "state_code": "QUS",
        "state_name": "Qusar",
        "country_id": 16,
        "country_code": "AZ",
        "country_name": "Azerbaijan",
        "latitude": "41.42750000",
        "longitude": "48.43020000",
        "timezone": null,
        "wikiDataId": "Q145715"
    },
    {
        "id": 8165,
        "name": "Samur",
        "state_id": 588,
        "state_code": "QUS",
        "state_name": "Qusar",
        "country_id": 16,
        "country_code": "AZ",
        "country_name": "Azerbaijan",
        "latitude": "41.63671000",
        "longitude": "48.43028000",
        "timezone": null,
        "wikiDataId": "Q4140710"
    },
    {
        "id": 8214,
        "name": "Əhmədbəyli",
        "state_id": 557,
        "state_code": "SAT",
        "state_name": "Saatly",
        "country_id": 16,
        "country_code": "AZ",
        "country_name": "Azerbaijan",
        "latitude": "39.88074000",
        "longitude": "48.39158000",
        "timezone": null,
        "wikiDataId": "Q4591920"
    },
    {
        "id": 8160,
        "name": "Saatlı",
        "state_id": 557,
        "state_code": "SAT",
        "state_name": "Saatly",
        "country_id": 16,
        "country_code": "AZ",
        "country_name": "Azerbaijan",
        "latitude": "39.93214000",
        "longitude": "48.36892000",
        "timezone": null,
        "wikiDataId": "Q1013460"
    },
    {
        "id": 8161,
        "name": "Sabirabad",
        "state_id": 565,
        "state_code": "SAB",
        "state_name": "Sabirabad",
        "country_id": 16,
        "country_code": "AZ",
        "country_name": "Azerbaijan",
        "latitude": "40.00869000",
        "longitude": "48.47701000",
        "timezone": null,
        "wikiDataId": "Q2148635"
    },
    {
        "id": 8141,
        "name": "Qaraçala",
        "state_id": 545,
        "state_code": "SAL",
        "state_name": "Salyan",
        "country_id": 16,
        "country_code": "AZ",
        "country_name": "Azerbaijan",
        "latitude": "39.81614000",
        "longitude": "48.93792000",
        "timezone": null,
        "wikiDataId": "Q4120929"
    },
    {
        "id": 8164,
        "name": "Salyan",
        "state_id": 545,
        "state_code": "SAL",
        "state_name": "Salyan",
        "country_id": 16,
        "country_code": "AZ",
        "country_name": "Azerbaijan",
        "latitude": "39.59621000",
        "longitude": "48.98479000",
        "timezone": null,
        "wikiDataId": "Q4618136"
    },
    {
        "id": 8140,
        "name": "Qarayeri",
        "state_id": 536,
        "state_code": "SMX",
        "state_name": "Samukh",
        "country_id": 16,
        "country_code": "AZ",
        "country_name": "Azerbaijan",
        "latitude": "40.78674000",
        "longitude": "46.31365000",
        "timezone": null,
        "wikiDataId": "Q4140315"
    },
    {
        "id": 8156,
        "name": "Qırmızı Samux",
        "state_id": 536,
        "state_code": "SMX",
        "state_name": "Samukh",
        "country_id": 16,
        "country_code": "AZ",
        "country_name": "Azerbaijan",
        "latitude": "40.93972000",
        "longitude": "46.37889000",
        "timezone": null,
        "wikiDataId": "Q4913690"
    },
    {
        "id": 8166,
        "name": "Samux",
        "state_id": 536,
        "state_code": "SMX",
        "state_name": "Samukh",
        "country_id": 16,
        "country_code": "AZ",
        "country_name": "Azerbaijan",
        "latitude": "40.76485000",
        "longitude": "46.40868000",
        "timezone": null,
        "wikiDataId": "Q2583107"
    },
    {
        "id": 8074,
        "name": "Divichibazar",
        "state_id": 591,
        "state_code": "SBN",
        "state_name": "Shabran",
        "country_id": 16,
        "country_code": "AZ",
        "country_name": "Azerbaijan",
        "latitude": "41.20117000",
        "longitude": "48.98712000",
        "timezone": null,
        "wikiDataId": "Q387971"
    },
    {
        "id": 8176,
        "name": "Sheki",
        "state_id": 518,
        "state_code": "SA",
        "state_name": "Shaki",
        "country_id": 16,
        "country_code": "AZ",
        "country_name": "Azerbaijan",
        "latitude": "41.19194000",
        "longitude": "47.17056000",
        "timezone": null,
        "wikiDataId": "Q234783"
    },
    {
        "id": 8057,
        "name": "Baş Göynük",
        "state_id": 586,
        "state_code": "SAK",
        "state_name": "Shaki",
        "country_id": 16,
        "country_code": "AZ",
        "country_name": "Azerbaijan",
        "latitude": "41.32582000",
        "longitude": "47.11357000",
        "timezone": null,
        "wikiDataId": "Q4875325"
    },
    {
        "id": 8173,
        "name": "Shamakhi",
        "state_id": 529,
        "state_code": "SMI",
        "state_name": "Shamakhi",
        "country_id": 16,
        "country_code": "AZ",
        "country_name": "Azerbaijan",
        "latitude": "40.63141000",
        "longitude": "48.64137000",
        "timezone": null,
        "wikiDataId": "Q388224"
    },
    {
        "id": 8075,
        "name": "Dolyar",
        "state_id": 583,
        "state_code": "SKR",
        "state_name": "Shamkir",
        "country_id": 16,
        "country_code": "AZ",
        "country_name": "Azerbaijan",
        "latitude": "40.86278000",
        "longitude": "46.03493000",
        "timezone": null,
        "wikiDataId": "Q4154188"
    },
    {
        "id": 8077,
        "name": "Dzagam",
        "state_id": 583,
        "state_code": "SKR",
        "state_name": "Shamkir",
        "country_id": 16,
        "country_code": "AZ",
        "country_name": "Azerbaijan",
        "latitude": "40.90330000",
        "longitude": "45.88564000",
        "timezone": null,
        "wikiDataId": "Q4140363"
    },
    {
        "id": 8143,
        "name": "Qasım İsmayılov",
        "state_id": 583,
        "state_code": "SKR",
        "state_name": "Shamkir",
        "country_id": 16,
        "country_code": "AZ",
        "country_name": "Azerbaijan",
        "latitude": "40.81243000",
        "longitude": "46.25938000",
        "timezone": null,
        "wikiDataId": "Q7267065"
    },
    {
        "id": 8174,
        "name": "Shamkhor",
        "state_id": 583,
        "state_code": "SKR",
        "state_name": "Shamkir",
        "country_id": 16,
        "country_code": "AZ",
        "country_name": "Azerbaijan",
        "latitude": "40.82975000",
        "longitude": "46.01780000",
        "timezone": null,
        "wikiDataId": "Q390783"
    },
    {
        "id": 8212,
        "name": "Şirvan",
        "state_id": 520,
        "state_code": "SR",
        "state_name": "Shirvan",
        "country_id": 16,
        "country_code": "AZ",
        "country_name": "Azerbaijan",
        "latitude": "39.93778000",
        "longitude": "48.92900000",
        "timezone": null,
        "wikiDataId": "Q2159352"
    },
    {
        "id": 8177,
        "name": "Shushi",
        "state_id": 592,
        "state_code": "SUS",
        "state_name": "Shusha",
        "country_id": 16,
        "country_code": "AZ",
        "country_name": "Azerbaijan",
        "latitude": "39.76006000",
        "longitude": "46.74989000",
        "timezone": null,
        "wikiDataId": "Q158903"
    },
    {
        "id": 8083,
        "name": "Gilgilçay",
        "state_id": 584,
        "state_code": "SIY",
        "state_name": "Siazan",
        "country_id": 16,
        "country_code": "AZ",
        "country_name": "Azerbaijan",
        "latitude": "41.13932000",
        "longitude": "49.09038000",
        "timezone": null,
        "wikiDataId": "Q4138326"
    },
    {
        "id": 8107,
        "name": "Kyzyl-Burun",
        "state_id": 584,
        "state_code": "SIY",
        "state_name": "Siazan",
        "country_id": 16,
        "country_code": "AZ",
        "country_name": "Azerbaijan",
        "latitude": "41.07811000",
        "longitude": "49.11564000",
        "timezone": null,
        "wikiDataId": "Q1017683"
    },
    {
        "id": 8070,
        "name": "Corat",
        "state_id": 582,
        "state_code": "SM",
        "state_name": "Sumqayit",
        "country_id": 16,
        "country_code": "AZ",
        "country_name": "Azerbaijan",
        "latitude": "40.57176000",
        "longitude": "49.70509000",
        "timezone": null,
        "wikiDataId": "Q4120953"
    },
    {
        "id": 8086,
        "name": "Hacı Zeynalabdin",
        "state_id": 582,
        "state_code": "SM",
        "state_name": "Sumqayit",
        "country_id": 16,
        "country_code": "AZ",
        "country_name": "Azerbaijan",
        "latitude": "40.62333000",
        "longitude": "49.55861000",
        "timezone": null,
        "wikiDataId": "Q4120954"
    },
    {
        "id": 8180,
        "name": "Sumqayıt",
        "state_id": 582,
        "state_code": "SM",
        "state_name": "Sumqayit",
        "country_id": 16,
        "country_code": "AZ",
        "country_name": "Azerbaijan",
        "latitude": "40.58972000",
        "longitude": "49.66861000",
        "timezone": null,
        "wikiDataId": "Q179833"
    },
    {
        "id": 8114,
        "name": "Martakert",
        "state_id": 519,
        "state_code": "TAR",
        "state_name": "Tartar",
        "country_id": 16,
        "country_code": "AZ",
        "country_name": "Azerbaijan",
        "latitude": "40.21127000",
        "longitude": "46.82135000",
        "timezone": null,
        "wikiDataId": "Q794712"
    },
    {
        "id": 8182,
        "name": "Terter",
        "state_id": 519,
        "state_code": "TAR",
        "state_name": "Tartar",
        "country_id": 16,
        "country_code": "AZ",
        "country_name": "Azerbaijan",
        "latitude": "40.34201000",
        "longitude": "46.93161000",
        "timezone": null,
        "wikiDataId": "Q2268790"
    },
    {
        "id": 8207,
        "name": "Çatax",
        "state_id": 533,
        "state_code": "TOV",
        "state_name": "Tovuz",
        "country_id": 16,
        "country_code": "AZ",
        "country_name": "Azerbaijan",
        "latitude": "40.72622000",
        "longitude": "45.55919000",
        "timezone": null,
        "wikiDataId": "Q4992165"
    },
    {
        "id": 8209,
        "name": "Çobansığnaq",
        "state_id": 533,
        "state_code": "TOV",
        "state_name": "Tovuz",
        "country_id": 16,
        "country_code": "AZ",
        "country_name": "Azerbaijan",
        "latitude": "40.75244000",
        "longitude": "45.70645000",
        "timezone": null,
        "wikiDataId": "Q12712919"
    },
    {
        "id": 8076,
        "name": "Dondar Quşçu",
        "state_id": 533,
        "state_code": "TOV",
        "state_name": "Tovuz",
        "country_id": 16,
        "country_code": "AZ",
        "country_name": "Azerbaijan",
        "latitude": "40.95390000",
        "longitude": "45.61942000",
        "timezone": null,
        "wikiDataId": "Q4993012"
    },
    {
        "id": 8139,
        "name": "Qaraxanlı",
        "state_id": 533,
        "state_code": "TOV",
        "state_name": "Tovuz",
        "country_id": 16,
        "country_code": "AZ",
        "country_name": "Azerbaijan",
        "latitude": "41.04358000",
        "longitude": "45.65527000",
        "timezone": null,
        "wikiDataId": "Q4991541"
    },
    {
        "id": 8183,
        "name": "Tovuz",
        "state_id": 533,
        "state_code": "TOV",
        "state_name": "Tovuz",
        "country_id": 16,
        "country_code": "AZ",
        "country_name": "Azerbaijan",
        "latitude": "40.99249000",
        "longitude": "45.62838000",
        "timezone": null,
        "wikiDataId": "Q1026084"
    },
    {
        "id": 8193,
        "name": "Yanıqlı",
        "state_id": 533,
        "state_code": "TOV",
        "state_name": "Tovuz",
        "country_id": 16,
        "country_code": "AZ",
        "country_name": "Azerbaijan",
        "latitude": "40.84320000",
        "longitude": "45.68030000",
        "timezone": null,
        "wikiDataId": "Q4991826"
    },
    {
        "id": 8185,
        "name": "Ujar",
        "state_id": 539,
        "state_code": "UCA",
        "state_name": "Ujar",
        "country_id": 16,
        "country_code": "AZ",
        "country_name": "Azerbaijan",
        "latitude": "40.51902000",
        "longitude": "47.65423000",
        "timezone": null,
        "wikiDataId": "Q646809"
    },
    {
        "id": 8194,
        "name": "Yardımlı",
        "state_id": 550,
        "state_code": "YAR",
        "state_name": "Yardymli",
        "country_id": 16,
        "country_code": "AZ",
        "country_name": "Azerbaijan",
        "latitude": "38.90771000",
        "longitude": "48.24052000",
        "timezone": null,
        "wikiDataId": "Q4991826"
    },
    {
        "id": 8198,
        "name": "Yevlakh",
        "state_id": 538,
        "state_code": "YE",
        "state_name": "Yevlakh",
        "country_id": 16,
        "country_code": "AZ",
        "country_name": "Azerbaijan",
        "latitude": "40.61832000",
        "longitude": "47.15014000",
        "timezone": null,
        "wikiDataId": "Q175459"
    },
    {
        "id": 8043,
        "name": "Aran",
        "state_id": 523,
        "state_code": "YEV",
        "state_name": "Yevlakh",
        "country_id": 16,
        "country_code": "AZ",
        "country_name": "Azerbaijan",
        "latitude": "40.62528000",
        "longitude": "46.97556000",
        "timezone": null,
        "wikiDataId": "Q4068504"
    },
    {
        "id": 8138,
        "name": "Qaramanlı",
        "state_id": 523,
        "state_code": "YEV",
        "state_name": "Yevlakh",
        "country_id": 16,
        "country_code": "AZ",
        "country_name": "Azerbaijan",
        "latitude": "40.48135000",
        "longitude": "46.99339000",
        "timezone": null,
        "wikiDataId": "Q5070570"
    },
    {
        "id": 8117,
        "name": "Mincivan",
        "state_id": 581,
        "state_code": "ZAN",
        "state_name": "Zangilan",
        "country_id": 16,
        "country_code": "AZ",
        "country_name": "Azerbaijan",
        "latitude": "39.03023000",
        "longitude": "46.72329000",
        "timezone": null,
        "wikiDataId": "Q2528138"
    },
    {
        "id": 8202,
        "name": "Zangilan",
        "state_id": 581,
        "state_code": "ZAN",
        "state_name": "Zangilan",
        "country_id": 16,
        "country_code": "AZ",
        "country_name": "Azerbaijan",
        "latitude": "39.08371000",
        "longitude": "46.65988000",
        "timezone": null,
        "wikiDataId": "Q249226"
    },
    {
        "id": 8040,
        "name": "Aliabad",
        "state_id": 566,
        "state_code": "ZAQ",
        "state_name": "Zaqatala",
        "country_id": 16,
        "country_code": "AZ",
        "country_name": "Azerbaijan",
        "latitude": "41.48290000",
        "longitude": "46.63483000",
        "timezone": null,
        "wikiDataId": "Q3651686"
    },
    {
        "id": 8079,
        "name": "Faldarlı",
        "state_id": 566,
        "state_code": "ZAQ",
        "state_name": "Zaqatala",
        "country_id": 16,
        "country_code": "AZ",
        "country_name": "Azerbaijan",
        "latitude": "41.46868000",
        "longitude": "46.51579000",
        "timezone": null,
        "wikiDataId": "Q5070803"
    },
    {
        "id": 8112,
        "name": "Mamrux",
        "state_id": 566,
        "state_code": "ZAQ",
        "state_name": "Zaqatala",
        "country_id": 16,
        "country_code": "AZ",
        "country_name": "Azerbaijan",
        "latitude": "41.54243000",
        "longitude": "46.76700000",
        "timezone": null,
        "wikiDataId": "Q4967860"
    },
    {
        "id": 8137,
        "name": "Qandax",
        "state_id": 566,
        "state_code": "ZAQ",
        "state_name": "Zaqatala",
        "country_id": 16,
        "country_code": "AZ",
        "country_name": "Azerbaijan",
        "latitude": "41.47546000",
        "longitude": "46.54128000",
        "timezone": null,
        "wikiDataId": "Q5074564"
    },
    {
        "id": 8203,
        "name": "Zaqatala",
        "state_id": 566,
        "state_code": "ZAQ",
        "state_name": "Zaqatala",
        "country_id": 16,
        "country_code": "AZ",
        "country_name": "Azerbaijan",
        "latitude": "41.63160000",
        "longitude": "46.64479000",
        "timezone": null,
        "wikiDataId": "Q147548"
    },
    {
        "id": 8204,
        "name": "Zardob",
        "state_id": 576,
        "state_code": "ZAR",
        "state_name": "Zardab",
        "country_id": 16,
        "country_code": "AZ",
        "country_name": "Azerbaijan",
        "latitude": "40.21840000",
        "longitude": "47.71214000",
        "timezone": null,
        "wikiDataId": "Q147548"
    }
]